[{"department":"Animal Science","url":"https:\/\/cals.cornell.edu\/animal-science","faculty_page":"https:\/\/cals.cornell.edu\/animal-science\/about\/people"},{"department":"Charles H. Dyson School of Applied Economics and Management","url":"https:\/\/dyson.cornell.edu\/","faculty_page":"https:\/\/dyson.cornell.edu\/faculty-research\/search\/"},{"department":"Biological and Environmental Engineering","url":"https:\/\/bee.cals.cornell.edu\/","faculty_page":"https:\/\/cals.cornell.edu\/biological-environmental-engineering\/about\/people\/faculty"},{"department":"Computational Biology","url":"https:\/\/compbio.cornell.edu\/","faculty_page":"https:\/\/compbio.cornell.edu\/people\/faculty"},{"department":"Communication","url":"https:\/\/cals.cornell.edu\/communication","faculty_page":"https:\/\/cals.cornell.edu\/communication\/about-us\/people"},{"department":"Earth and Atmospheric Sciences","url":"https:\/\/www.eas.cornell.edu\/eas","faculty_page":"https:\/\/www.eas.cornell.edu\/eas\/faculty-directory"},{"department":"Ecology and Evolutionary Biology","url":"https:\/\/ecologyandevolution.cornell.edu\/","faculty_page":"https:\/\/ecologyandevolution.cornell.edu\/faculty"},{"department":"Entomology","url":"https:\/\/entomology.cals.cornell.edu\/","faculty_page":"https:\/\/entomology.cals.cornell.edu\/people\/faculty-and-senior-academic-staff"},{"department":"Food Science","url":"https:\/\/cals.cornell.edu\/food-science","faculty_page":"https:\/\/cals.cornell.edu\/food-science\/about\/people"},{"department":"Global Development","url":"https:\/\/cals.cornell.edu\/global-development","faculty_page":"https:\/\/cals.cornell.edu\/global-development\/about\/people\/faculty"},{"department":"School of Integrative Plant Science","url":"https:\/\/cals.cornell.edu\/school-integrative-plant-science","faculty_page":"https:\/\/cals.cornell.edu\/school-integrative-plant-science\/about\/people\/faculty-senior-academics"},{"department":"Landscape Architecture","url":"https:\/\/cals.cornell.edu\/landscape-architecture","faculty_page":"https:\/\/cals.cornell.edu\/landscape-architecture\/people"},{"department":"Microbiology","url":"https:\/\/micro.cornell.edu\/","faculty_page":"https:\/\/cals.cornell.edu\/microbiology\/about-us\/directory"},{"department":"Molecular Biology and Genetics","url":"https:\/\/mbg.cornell.edu\/","faculty_page":"https:\/\/mbg.cornell.edu\/people\/faculty"},{"department":"Natural Resources","url":"https:\/\/cals.cornell.edu\/natural-resources-environment","faculty_page":"https:\/\/cals.cornell.edu\/natural-resources-environment\/about-us\/people\/faculty-academic-staff"},{"department":"Neurobiology and Behavior","url":"https:\/\/nbb.cornell.edu\/","faculty_page":"https:\/\/nbb.cornell.edu\/faculty"},{"department":"Nutritional Sciences","url":"https:\/\/www.human.cornell.edu\/dns","faculty_page":"https:\/\/www.human.cornell.edu\/dns\/about\/people"},{"department":"Statistics and Data Science","url":"https:\/\/stat.cornell.edu\/","faculty_page":"https:\/\/stat.cornell.edu\/people\/faculty"},{"department":"Architecture","url":"https:\/\/aap.cornell.edu\/academics\/architecture","faculty_page":"https:\/\/aap.cornell.edu\/academics\/faculty?department=8&location=&faculty_status=13831&focus_areas=&keyword="},{"department":"Art","url":"https:\/\/aap.cornell.edu\/academics\/art","faculty_page":"https:\/\/aap.cornell.edu\/academics\/faculty?department=7&location=&faculty_status=13831&focus_areas=&keyword="},{"department":"City and Regional Planning","url":"https:\/\/aap.cornell.edu\/academics\/department-city-and-regional-planning","faculty_page":"https:\/\/aap.cornell.edu\/academics\/faculty?department=15&location=&faculty_status=13831&focus_areas=&keyword="},{"department":" Africana Studies","url":"https:\/\/africana.cornell.edu\/","faculty_page":"https:\/\/africana.cornell.edu\/faculty"},{"department":"Anthropology","url":"https:\/\/anthropology.cornell.edu\/","faculty_page":"https:\/\/anthropology.cornell.edu\/anthropology-faculty"},{"department":"Asian Studies","url":"https:\/\/asianstudies.cornell.edu\/","faculty_page":"https:\/\/asianstudies.cornell.edu\/faculty"},{"department":"Astronomy","url":"https:\/\/astro.cornell.edu\/","faculty_page":"https:\/\/astro.cornell.edu\/faculty"},{"department":"Chemistry and Chemical Biology","url":"https:\/\/chemistry.cornell.edu\/","faculty_page":"https:\/\/chemistry.cornell.edu\/faculty"},{"department":"Classics","url":"https:\/\/classics.cornell.edu\/","faculty_page":"https:\/\/classics.cornell.edu\/faculty"},{"department":"Comparative Literature","url":"https:\/\/complit.cornell.edu\/","faculty_page":"https:\/\/complit.cornell.edu\/department-faculty"},{"department":"Ecology & Evolutionary Biology","url":"https:\/\/ecologyandevolution.cornell.edu\/","faculty_page":"https:\/\/ecologyandevolution.cornell.edu\/faculty"},{"department":"Economics","url":"https:\/\/economics.cornell.edu\/","faculty_page":"https:\/\/economics.cornell.edu\/faculty"},{"department":"English","url":"https:\/\/english.cornell.edu\/","faculty_page":"https:\/\/english.cornell.edu\/faculty"},{"department":"German Studies","url":"https:\/\/german.cornell.edu\/","faculty_page":"https:\/\/german.cornell.edu\/faculty"},{"department":" Government","url":"https:\/\/government.cornell.edu\/","faculty_page":"https:\/\/government.cornell.edu\/faculty"},{"department":"History","url":"http:\/\/history.arts.cornell.edu\/","faculty_page":"https:\/\/history.cornell.edu\/faculty"},{"department":"History of Art and Visual Studies","url":"https:\/\/arthistory.cornell.edu\/","faculty_page":"https:\/\/arthistory.cornell.edu\/faculty"},{"department":"Linguistics","url":"https:\/\/linguistics.cornell.edu\/","faculty_page":"https:\/\/linguistics.cornell.edu\/faculty"},{"department":"Mathematics","url":"https:\/\/math.cornell.edu\/","faculty_page":"https:\/\/math.cornell.edu\/faculty"},{"department":"Music","url":"https:\/\/music.cornell.edu\/","faculty_page":"https:\/\/music.cornell.edu\/faculty"},{"department":"Near Eastern Studies","url":"https:\/\/neareasternstudies.cornell.edu\/","faculty_page":"https:\/\/neareasternstudies.cornell.edu\/faculty"},{"department":"Performing and Media Arts","url":"https:\/\/pma.cornell.edu\/","faculty_page":"https:\/\/pma.cornell.edu\/faculty"},{"department":"Sage School of Philosophy","url":"https:\/\/philosophy.cornell.edu\/","faculty_page":"https:\/\/philosophy.cornell.edu\/faculty"},{"department":"Physics","url":"https:\/\/physics.cornell.edu\/","faculty_page":"https:\/\/physics.cornell.edu\/faculty"},{"department":"Psychology","url":"https:\/\/psychology.cornell.edu\/","faculty_page":"https:\/\/psychology.cornell.edu\/faculty"},{"department":"Romance Studies","url":"https:\/\/romancestudies.cornell.edu\/","faculty_page":"https:\/\/romancestudies.cornell.edu\/faculty"},{"department":"Science and Technology Studies","url":"https:\/\/sts.cornell.edu\/","faculty_page":"https:\/\/sts.cornell.edu\/faculty"},{"department":"Sociology","url":"https:\/\/sociology.cornell.edu\/","faculty_page":"https:\/\/sociology.cornell.edu\/faculty"},{"department":"Peter and Stephanie Nolan School of Hotel Administration","url":"https:\/\/sha.cornell.edu\/","faculty_page":"https:\/\/sha.cornell.edu\/faculty-research\/search\/"},{"department":"Samuel Curtis Johnson Graduate School of Management","url":"https:\/\/www.johnson.cornell.edu\/","faculty_page":"https:\/\/www.johnson.cornell.edu\/faculty-research\/search\/"},{"department":"Computer Science","url":"http:\/\/www.cs.cornell.edu\/","faculty_page":"http:\/\/www.cs.cornell.edu\/people\/faculty"},{"department":"Information Science","url":"https:\/\/infosci.cornell.edu\/","faculty_page":"https:\/\/infosci.cornell.edu\/people\/faculty"},{"department":"School of Applied and Engineering Physics","url":"https:\/\/www.aep.cornell.edu\/aep","faculty_page":"https:\/\/www.aep.cornell.edu\/aep\/faculty-directory"},{"department":"Meinig School of Biomedical Engineering","url":"https:\/\/www.bme.cornell.edu\/bme","faculty_page":"https:\/\/www.bme.cornell.edu\/bme\/faculty-directory"},{"department":"Smith School of Chemical and Biomolecular Engineering","url":"https:\/\/www.cheme.cornell.edu\/cbe","faculty_page":"https:\/\/www.cheme.cornell.edu\/cbe\/faculty-directory"},{"department":"School of Civil and Environmental Engineering","url":"https:\/\/www.cee.cornell.edu\/cee","faculty_page":"https:\/\/www.cee.cornell.edu\/cee\/faculty-directory"},{"department":"Computer Science","url":"http:\/\/www.cs.cornell.edu\/","faculty_page":"https:\/\/www.cs.cornell.edu\/people\/faculty"},{"department":"School of Electrical and Computer Engineering","url":"https:\/\/www.ece.cornell.edu\/ece","faculty_page":"https:\/\/www.ece.cornell.edu\/ece\/faculty-directory"},{"department":"Materials Science and Engineering","url":"https:\/\/www.mse.cornell.edu\/mse","faculty_page":"https:\/\/www.mse.cornell.edu\/mse\/faculty-directory"},{"department":"Sibley School of Mechanical and Aerospace Engineering ","url":"https:\/\/www.mae.cornell.edu\/mae","faculty_page":"https:\/\/www.mae.cornell.edu\/mae\/faculty-directory"},{"department":"School of Operations Research and Information Engineering","url":"https:\/\/www.orie.cornell.edu\/orie","faculty_page":"https:\/\/www.orie.cornell.edu\/orie\/faculty-directory"},{"department":"College of Human Ecology","url":"https:\/\/www.human.cornell.edu\/","faculty_page":"https:\/\/www.human.cornell.edu\/about\/people?combine=&field_bio_department_2_target_id=All&field_bio_employee_type_value=Faculty"},{"department":"School of Industrial and Labor Relations","url":"https:\/\/www.ilr.cornell.edu\/","faculty_page":"https:\/\/www.ilr.cornell.edu\/people"}]